odoo10_addon_l10n_fr_department_oversea-10.0.1.0.0-py2.7-nspkg.pth
odoo10_addon_l10n_fr_department_oversea-10.0.1.0.0.dist-info/top_level.txt
odoo10_addon_l10n_fr_department_oversea-10.0.1.0.0.dist-info/WHEEL
odoo10_addon_l10n_fr_department_oversea-10.0.1.0.0.dist-info/RECORD
odoo10_addon_l10n_fr_department_oversea-10.0.1.0.0.dist-info/metadata.json
odoo10_addon_l10n_fr_department_oversea-10.0.1.0.0.dist-info/DESCRIPTION.rst
odoo10_addon_l10n_fr_department_oversea-10.0.1.0.0.dist-info/METADATA
odoo10_addon_l10n_fr_department_oversea-10.0.1.0.0.dist-info/namespace_packages.txt
odoo/addons/l10n_fr_department_oversea/__manifest__.py
odoo/addons/l10n_fr_department_oversea/post_install.py
odoo/addons/l10n_fr_department_oversea/__init__.py
odoo/addons/l10n_fr_department_oversea/README.rst
odoo/addons/l10n_fr_department_oversea/data/res_country_state.xml
odoo/addons/l10n_fr_department_oversea/data/res_country_department.xml
odoo/addons/l10n_fr_department_oversea/tests/test_department_oversea.py
odoo/addons/l10n_fr_department_oversea/tests/__init__.py
